http_content_parser/__init__.py
http_content_parser/api_parser.py
http_content_parser/curl_parser.py
http_content_parser/openapi_parser.py
http_content_parser/param_util.py
http_content_parser/postman_parser.py
http_content_parser/req_data.py
http_content_parser/swagger2_parser.py
http_content_parser-0.0.26.dist-info/METADATA
http_content_parser-0.0.26.dist-info/WHEEL
http_content_parser-0.0.26.dist-info/licenses/LICENSE
http_content_parser-0.0.26.dist-info/RECORD
