Metadata-Version: 2.4
Name: http_content_parser
Version: 0.0.26
Summary: parse http's payload and response
Author-email: leo <suleiabc@gmail.com>
License-File: LICENSE
Classifier: License :: OSI Approved :: MIT License
Classifier: Operating System :: OS Independent
Classifier: Programming Language :: Python :: 3
Requires-Python: >=3.8
